kraken_convert/__init__.py
kraken_convert/json_helper.py
kraken_convert/kraken_convert.py
kraken_convert/mapping_engine.py
kraken_convert/to_dot.py
kraken_convert/maps/__init__.py
kraken_convert/maps/office.py
kraken_convert-0.0.7.dist-info/LICENSE.txt
kraken_convert-0.0.7.dist-info/METADATA
kraken_convert-0.0.7.dist-info/WHEEL
kraken_convert-0.0.7.dist-info/top_level.txt
kraken_convert-0.0.7.dist-info/RECORD
