Metadata-Version: 2.1
Name: kraken-convert
Version: 0.0.7
Summary: Kraken convert
Home-page: https://github.com/tactik8/krakenconvert2
Author: Tactik8
Author-email: info@tactik8.com
License: MIT
Classifier: License :: OSI Approved :: MIT License
Classifier: Programming Language :: Python :: 3
Classifier: Programming Language :: Python :: 3.10
License-File: LICENSE.txt
Requires-Dist: python-dateutil
Requires-Dist: xmltodict
Requires-Dist: requests
